Metadata-Version: 1.0
Name: tigran-test
Version: 0.1
Summary: My package
Home-page: https://github.com/ruperson/tigran_test
Author: UNKNOWN
Author-email: UNKNOWN
License: UNKNOWN
Platform: UNKNOWN
